snsphd/__init__.py
snsphd/clock.py
snsphd/help.py
snsphd/hist.py
snsphd/layout.py
snsphd/obj.py
snsphd/viz.py
snsphd-0.1.5.dist-info/LICENSE
snsphd-0.1.5.dist-info/METADATA
snsphd-0.1.5.dist-info/WHEEL
snsphd-0.1.5.dist-info/RECORD
