Metadata-Version: 2.1
Name: snsphd
Version: 0.1.5
Summary: Utility and styling functions for A. Mueller's phd thesis
Home-page: https://github.com/sansseriff/snsphd
License: MIT
Author: Andrew Mueller
Author-email: andrewstermueller@gmail.com
Requires-Python: >=3.10,<4.0
Classifier: License :: OSI Approved :: MIT License
Classifier: Programming Language :: Python :: 3
Classifier: Programming Language :: Python :: 3.10
Classifier: Programming Language :: Python :: 3.11
Classifier: Programming Language :: Python :: 3.12
Requires-Dist: bokeh (>=3.2.0,<4.0.0)
Requires-Dist: ipython (>=8.14.0,<9.0.0)
Requires-Dist: matplotlib (>=3.7.2,<4.0.0)
Requires-Dist: numba (>=0.60.0)
Requires-Dist: numpy (>=2.0,<3.0)
Requires-Dist: orjson (>=3.9.1,<4.0.0)
Requires-Dist: scipy (>=1.11.1,<2.0.0)
Project-URL: Repository, https://github.com/sansseriff/snsphd
